MANIFEST.in
README.txt
setup.py
FLAM/FlamGUI.py
FLAM/QTCSS.py
FLAM/dbBase.py
FLAM/dbQueries.py
FLAM/folderStructure.py
FLAM/installer.py
FLAM/icons/downArrow.png
FLAM/icons/flam_icon.png
FLAM/icons/temp.png
ha_flam.egg-info/PKG-INFO
ha_flam.egg-info/SOURCES.txt
ha_flam.egg-info/dependency_links.txt
ha_flam.egg-info/not-zip-safe
ha_flam.egg-info/requires.txt
ha_flam.egg-info/top_level.txt