Metadata-Version: 1.0
Name: ha-flam
Version: 0.1.3
Summary: FreeLanceAssetManager.
Home-page: https://github.com/halbaugh/FLAM
Author: Hunter Albaugh
Author-email: hunteralbaugh@gmail.com
License: LICENSE.txt
Platform: UNKNOWN
